{
  "nextEntryId": 52,
  "nodes": [
    {
      "id": "1",
      "name": "Tile Set",
      "type": "tileSet"
    },
    {
      "id": "34",
      "name": "TileSet 2",
      "type": "tileSet"
    },
    {
      "id": "2",
      "name": "Map",
      "type": "tileMap"
    },
    {
      "id": "33",
      "name": "Tutorial Map",
      "type": "tileMap"
    },
    {
      "id": "43",
      "name": "CV Map",
      "type": "tileMap"
    },
    {
      "id": "13",
      "name": "Player",
      "type": null,
      "children": [
        {
          "id": "4",
          "name": "Sprite",
          "type": "sprite"
        },
        {
          "id": "5",
          "name": "Behavior",
          "type": "script"
        }
      ]
    },
    {
      "id": "24",
      "name": "Scenas",
      "type": null,
      "children": [
        {
          "id": "31",
          "name": "Scene tutorial",
          "type": "scene"
        },
        {
          "id": "0",
          "name": "Scene",
          "type": "scene"
        },
        {
          "id": "41",
          "name": "Scena CV EN",
          "type": "scene"
        },
        {
          "id": "44",
          "name": "Scena CV ES",
          "type": "scene"
        }
      ]
    },
    {
      "id": "20",
      "name": "Fade",
      "type": null,
      "children": [
        {
          "id": "21",
          "name": "Fade Manager",
          "type": "script"
        },
        {
          "id": "22",
          "name": "Black Screen",
          "type": "sprite"
        }
      ]
    },
    {
      "id": "18",
      "name": "Interactions",
      "type": null,
      "children": [
        {
          "id": "19",
          "name": "DeathBehavior",
          "type": "script"
        },
        {
          "id": "46",
          "name": "Teleport Behavior",
          "type": "script"
        }
      ]
    },
    {
      "id": "14",
      "name": "Camera",
      "type": null,
      "children": [
        {
          "id": "15",
          "name": "CameraBehavior",
          "type": "script"
        }
      ]
    },
    {
      "id": "39",
      "name": "Arrow Up",
      "type": "sprite"
    },
    {
      "id": "8",
      "name": "T-Rex",
      "type": "sprite"
    },
    {
      "id": "40",
      "name": "Arrow Right",
      "type": "sprite"
    },
    {
      "id": "6",
      "name": "Background",
      "type": "sprite"
    },
    {
      "id": "42",
      "name": "CV EN",
      "type": "sprite"
    },
    {
      "id": "45",
      "name": "CV ES",
      "type": "sprite"
    },
    {
      "id": "47",
      "name": "Keys1",
      "type": "sprite"
    },
    {
      "id": "48",
      "name": "Keys2",
      "type": "sprite"
    },
    {
      "id": "49",
      "name": "Keys3",
      "type": "sprite"
    },
    {
      "id": "51",
      "name": "LostTY",
      "type": "sprite"
    },
    {
      "id": "26",
      "name": "parallax",
      "type": null,
      "children": [
        {
          "id": "27",
          "name": "parallax 1",
          "type": "sprite"
        },
        {
          "id": "28",
          "name": "parallax 2",
          "type": "sprite"
        },
        {
          "id": "30",
          "name": "parallax 3",
          "type": "sprite"
        },
        {
          "id": "29",
          "name": "parallax 4",
          "type": "sprite"
        },
        {
          "id": "35",
          "name": "ParallaxBehavior",
          "type": "script"
        }
      ]
    },
    {
      "id": "50",
      "name": "Lost Constellation",
      "type": "sound"
    }
  ]
}